odoo/addons/stock_barcodes/README.rst
odoo/addons/stock_barcodes/__init__.py
odoo/addons/stock_barcodes/__manifest__.py
odoo/addons/stock_barcodes/i18n/es.po
odoo/addons/stock_barcodes/i18n/stock_barcodes.pot
odoo/addons/stock_barcodes/models/__init__.py
odoo/addons/stock_barcodes/models/stock_barcodes_read_log.py
odoo/addons/stock_barcodes/models/stock_inventory.py
odoo/addons/stock_barcodes/models/stock_picking.py
odoo/addons/stock_barcodes/models/stock_picking_type.py
odoo/addons/stock_barcodes/readme/CONTRIBUTORS.rst
odoo/addons/stock_barcodes/readme/DESCRIPTION.rst
odoo/addons/stock_barcodes/readme/HISTORY.rst
odoo/addons/stock_barcodes/readme/ROADMAP.rst
odoo/addons/stock_barcodes/readme/USAGE.rst
odoo/addons/stock_barcodes/security/ir.model.access.csv
odoo/addons/stock_barcodes/static/description/icon.png
odoo/addons/stock_barcodes/static/description/index.html
odoo/addons/stock_barcodes/static/src/css/stock.css
odoo/addons/stock_barcodes/static/src/img/scan.png
odoo/addons/stock_barcodes/static/src/js/basic_field.js
odoo/addons/stock_barcodes/static/src/js/stock_barcodes.js
odoo/addons/stock_barcodes/tests/__init__.py
odoo/addons/stock_barcodes/tests/test_stock_barcodes.py
odoo/addons/stock_barcodes/tests/test_stock_barcodes_inventory.py
odoo/addons/stock_barcodes/tests/test_stock_barcodes_new_lot.py
odoo/addons/stock_barcodes/tests/test_stock_barcodes_picking.py
odoo/addons/stock_barcodes/views/assets.xml
odoo/addons/stock_barcodes/views/stock_inventory_views.xml
odoo/addons/stock_barcodes/views/stock_picking_views.xml
odoo/addons/stock_barcodes/wizard/__init__.py
odoo/addons/stock_barcodes/wizard/stock_barcodes_read.py
odoo/addons/stock_barcodes/wizard/stock_barcodes_read_inventory.py
odoo/addons/stock_barcodes/wizard/stock_barcodes_read_inventory_views.xml
odoo/addons/stock_barcodes/wizard/stock_barcodes_read_picking.py
odoo/addons/stock_barcodes/wizard/stock_barcodes_read_picking_views.xml
odoo/addons/stock_barcodes/wizard/stock_barcodes_read_views.xml
odoo11_addon_stock_barcodes-11.0.2.0.3.dist-info/METADATA
odoo11_addon_stock_barcodes-11.0.2.0.3.dist-info/WHEEL
odoo11_addon_stock_barcodes-11.0.2.0.3.dist-info/top_level.txt
odoo11_addon_stock_barcodes-11.0.2.0.3.dist-info/RECORD
